ErisPulse_AIChat/Core.py
ErisPulse_AIChat/__init__.py
erispulse_aichat-3.0.4.dist-info/licenses/LICENSE
erispulse_aichat-3.0.4.dist-info/METADATA
erispulse_aichat-3.0.4.dist-info/WHEEL
erispulse_aichat-3.0.4.dist-info/entry_points.txt
erispulse_aichat-3.0.4.dist-info/top_level.txt
erispulse_aichat-3.0.4.dist-info/RECORD
