Metadata-Version: 2.4
Name: ErisPulse-AIChat
Version: 3.0.4
Summary: ErisPulse AIChat 聊天机器人模块
Author-email: wsu2059q <wsu2059@qq.com>
License: MIT License
Project-URL: homepage, https://github.com/wsu2059q/ErisPulse-AIChat
Requires-Python: >=3.9
License-File: LICENSE
Requires-Dist: ErisPulse-OpenAI
Dynamic: license-file
